sqlencode/__init__.py
sqlencode/__utilfuncs__.py
sqlencode/encoder.py
sqlencode/onehotsql.py
sqlencode-0.0.3.dist-info/LICENSE
sqlencode-0.0.3.dist-info/METADATA
sqlencode-0.0.3.dist-info/WHEEL
sqlencode-0.0.3.dist-info/top_level.txt
sqlencode-0.0.3.dist-info/RECORD
