Metadata-Version: 2.1
Name: sqlencode
Version: 0.0.3
Summary: Python package to generate sql string for encoding categorical variables.
Home-page: https://github.com/mooseful/sqlencode
Author: Mohammed Taboun
Author-email: mtaboun@gmail.com
License: UNKNOWN
Project-URL: Bug Tracker, https://github.com/mooseful/sqlencode/issues
Platform: UNKNOWN
Classifier: Programming Language :: Python :: 3
Classifier: License :: OSI Approved :: MIT License
Classifier: Operating System :: OS Independent
Requires-Python: >=3.8
License-File: LICENSE
